spready/__init__.py
spready/app.py
spready/cli.py
spready/config.py
spready/decor.py
spready/dto.py
spready/job.py
spready/parser.py
spready/jobs/__init__.py
spready/jobs/myjob.py
spready-1.12.dist-info/METADATA
spready-1.12.dist-info/WHEEL
spready-1.12.dist-info/entry_points.txt
spready-1.12.dist-info/top_level.txt
spready-1.12.dist-info/RECORD
